{
  "exam_id": "ib-career-related",
  "exam_name": "IB Career-related Programme (IBCP)",
  "exam_code": "IBCP",
  "certifying_body": "International Baccalaureate",
  "certification_name": null,
  "version": null,
  "source_url": "https://www.ibo.org/programmes/career-related-programme/",
  "passing_score": null,
  "passing_score_scale": null,
  "total_questions": null,
  "question_types": [],
  "exam_format": "Mix of external examinations, internal assessments, and projects; varies by programme and subject",
  "duration_minutes": null,
  "exam_price_usd": 171.0,
  "exam_price_notes": "~$171 USD per exam session for DP subjects taken as part of CP.",
  "voucher_url": null,
  "exam_registration_url": null,
  "testing_centers": [],
  "online_proctoring_available": null,
  "id_requirements": null,
  "exam_rules": null,
  "certification_validity_years": null,
  "renewal_required": null,
  "renewal_options": null,
  "continuing_education_units": null,
  "available_languages": [],
  "target_audience": null,
  "recommended_experience": null,
  "prerequisites": [
    {
      "prerequisite_type": "recommended",
      "description": "Enrollment in an IB World School offering the CP",
      "is_required": false
    }
  ],
  "retake_policy": null,
  "domains": [
    {
      "id": "1",
      "name": "DP Courses (minimum 2)",
      "weight_percent": 40.0,
      "objectives": []
    },
    {
      "id": "2",
      "name": "Career-related Study",
      "weight_percent": 30.0,
      "objectives": []
    },
    {
      "id": "3",
      "name": "Core (Reflective Project, Language Dev, Service Learning, PPS)",
      "weight_percent": 30.0,
      "objectives": []
    }
  ],
  "official_objectives_url": null,
  "official_study_resources": [],
  "aliases": [
    "ib career programme",
    "ib career-related programme ibcp",
    "ib cp",
    "ib-career-related",
    "ibcp"
  ],
  "practice_url": "https://quizforge.ai/tests/ib-career-related"
}