{
  "exam_id": "clep-college-mathematics",
  "exam_name": "College Mathematics",
  "exam_code": "COLMAT",
  "certifying_body": "CLEP",
  "certification_name": null,
  "version": null,
  "source_url": "https://clep.collegeboard.org/clep-exams/college-mathematics",
  "passing_score": 50,
  "passing_score_scale": "0-80",
  "total_questions": 60,
  "question_types": [
    "Multiple Choice"
  ],
  "exam_format": "Multiple-choice (computer-based)",
  "duration_minutes": 90,
  "exam_price_usd": 93.0,
  "exam_price_notes": "$93 exam fee + ~$30 test center fee. Fee waivers for military/low-income.",
  "voucher_url": null,
  "exam_registration_url": "Register",
  "testing_centers": [],
  "online_proctoring_available": null,
  "id_requirements": null,
  "exam_rules": "A scientific (nongraphing) calculator, the TI-30XS MultiView™, is integrated into the exam software and available to students during the entire testing time. Students are expected to know how and when to make appropriate use of the calculator.",
  "certification_validity_years": null,
  "renewal_required": null,
  "renewal_options": null,
  "continuing_education_units": null,
  "available_languages": [
    "English"
  ],
  "target_audience": "Nonmathematics majors and majors in fields not requiring knowledge of advanced mathematics",
  "recommended_experience": "None specified",
  "prerequisites": [
    {
      "prerequisite_type": "experience",
      "description": "None specified",
      "is_required": false
    }
  ],
  "retake_policy": {
    "waiting_period_days": null,
    "max_attempts_per_year": null,
    "max_attempts_total": null,
    "notes": "Each institution reserves the right to set its own credit-granting policy, which may differ from the American Council on Education (ACE). Contact your college to find out the score required for credit and the number of credit hours granted."
  },
  "domains": [
    {
      "id": "Algebra and Functions",
      "name": "Algebra and Functions",
      "weight_percent": 20.0,
      "objectives": [
        {
          "id": "1",
          "title": "Solving equations, linear inequalities, and systems of linear equations by analytic and graphical methods",
          "sub_objectives": []
        },
        {
          "id": "2",
          "title": "Interpretation, representation, and evaluation of functions: numerical, graphical, symbolic, and descriptive methods",
          "sub_objectives": []
        },
        {
          "id": "3",
          "title": "Graphs of functions: translations, horizontal and vertical reflections, and symmetry about the x-axis, the y-axis, and the origin",
          "sub_objectives": []
        },
        {
          "id": "4",
          "title": "Linear and exponential growth",
          "sub_objectives": []
        },
        {
          "id": "5",
          "title": "Applications",
          "sub_objectives": []
        }
      ]
    },
    {
      "id": "Counting and Probability",
      "name": "Counting and Probability",
      "weight_percent": 10.0,
      "objectives": [
        {
          "id": "1",
          "title": "Counting problems: the multiplication rule, combinations, and permutations",
          "sub_objectives": []
        },
        {
          "id": "2",
          "title": "Probability: union, intersection, independent events, mutually exclusive events, complementary events, conditional probabilities, and expected value",
          "sub_objectives": []
        },
        {
          "id": "3",
          "title": "Applications",
          "sub_objectives": []
        }
      ]
    },
    {
      "id": "Data Analysis and Statistics",
      "name": "Data Analysis and Statistics",
      "weight_percent": 15.0,
      "objectives": [
        {
          "id": "1",
          "title": "Data interpretation and representation: tables, bar graphs, line graphs, circle graphs, pie charts, scatterplots, and histograms",
          "sub_objectives": []
        },
        {
          "id": "2",
          "title": "Numerical summaries of data: mean (average), median, mode, and range",
          "sub_objectives": []
        },
        {
          "id": "3",
          "title": "Standard deviation and normal distribution (conceptual questions only)",
          "sub_objectives": []
        },
        {
          "id": "4",
          "title": "Applications",
          "sub_objectives": []
        }
      ]
    },
    {
      "id": "Financial Mathematics",
      "name": "Financial Mathematics",
      "weight_percent": 20.0,
      "objectives": [
        {
          "id": "1",
          "title": "Percents, percent change, markups, discounts, taxes, profit, and loss",
          "sub_objectives": []
        },
        {
          "id": "2",
          "title": "Interest: simple, compound, continuous interest, effective interest rate, effective annual yield or annual percentage rate (APR)",
          "sub_objectives": []
        },
        {
          "id": "3",
          "title": "Present value and future value",
          "sub_objectives": []
        },
        {
          "id": "4",
          "title": "Applications",
          "sub_objectives": []
        }
      ]
    },
    {
      "id": "Geometry",
      "name": "Geometry",
      "weight_percent": 10.0,
      "objectives": [
        {
          "id": "1",
          "title": "Properties of triangles and quadrilaterals: perimeter, area, similarity, and the Pythagorean theorem",
          "sub_objectives": []
        },
        {
          "id": "2",
          "title": "Parallel and perpendicular lines",
          "sub_objectives": []
        },
        {
          "id": "3",
          "title": "Properties of circles: circumference, area, central angles, inscribed angles, and sectors",
          "sub_objectives": []
        },
        {
          "id": "4",
          "title": "Applications",
          "sub_objectives": []
        }
      ]
    },
    {
      "id": "Logic and Sets",
      "name": "Logic and Sets",
      "weight_percent": 15.0,
      "objectives": [
        {
          "id": "1",
          "title": "Logical operations and statements: conditional statements, conjunctions, disjunctions, negations, hypotheses, logical conclusions, converses, inverses, counterexamples, contrapositives, and logical equivalence",
          "sub_objectives": []
        },
        {
          "id": "2",
          "title": "Set relationships, subsets, disjoint sets, equality of sets, and Venn diagrams",
          "sub_objectives": []
        },
        {
          "id": "3",
          "title": "Operations on sets: union, intersection, and complement",
          "sub_objectives": []
        },
        {
          "id": "4",
          "title": "Applications",
          "sub_objectives": []
        }
      ]
    },
    {
      "id": "Numbers",
      "name": "Numbers",
      "weight_percent": 10.0,
      "objectives": [
        {
          "id": "1",
          "title": "Properties of numbers and their operations: integers and rational, irrational, and real numbers (including recognizing rational and irrational numbers)",
          "sub_objectives": []
        },
        {
          "id": "2",
          "title": "Elementary number theory: factors and divisibility, primes and composites, odd and even integers, and the fundamental theorem of arithmetic",
          "sub_objectives": []
        },
        {
          "id": "3",
          "title": "Measurement: unit conversion, scientific notation, and numerical precision",
          "sub_objectives": []
        },
        {
          "id": "4",
          "title": "Absolute value",
          "sub_objectives": []
        },
        {
          "id": "5",
          "title": "Applications",
          "sub_objectives": []
        }
      ]
    }
  ],
  "official_objectives_url": null,
  "official_study_resources": [
    {
      "resource_type": "official_study_guide",
      "title": "CLEP College Mathematics Examination Guide",
      "url": null,
      "provider": "CLEP",
      "is_official": true,
      "price_usd": 10.0,
      "notes": "PDF"
    },
    {
      "resource_type": "article",
      "title": "Study Resources: College Mathematics",
      "url": null,
      "provider": "CLEP",
      "is_official": true,
      "price_usd": null,
      "notes": "A study plan and list of online resources."
    },
    {
      "resource_type": "article",
      "title": "Sample Questions: College Mathematics",
      "url": null,
      "provider": "CLEP",
      "is_official": true,
      "price_usd": null,
      "notes": "Answer sample questions related to the College Mathematics exam."
    },
    {
      "resource_type": "article",
      "title": "What Your CLEP Score Means",
      "url": null,
      "provider": "CLEP",
      "is_official": true,
      "price_usd": null,
      "notes": "Guide to understanding how CLEP scores are calculated and credit-granting recommendations for all exams."
    },
    {
      "resource_type": "article",
      "title": "ACE Credit Recommendations",
      "url": null,
      "provider": "American Council on Education (ACE)",
      "is_official": true,
      "price_usd": null,
      "notes": "Recommendations for credit-granting scores from the American Council on Education."
    }
  ],
  "aliases": [
    "clep college mathematics",
    "clep-college-mathematics",
    "college math clep",
    "college mathematics",
    "colmat"
  ],
  "practice_url": "https://quizforge.ai/?q=College%20Mathematics"
}